_smc600.cp39-win_amd64.pyd
SMC600/LTSMC.dll
SMC600/LTSMC.h
SMC600/LTSMC.lib
SMC600/__init__.py
SMC600/_smc600.cp39-win_amd64.pyd
SMC600/smc600.h
SMC600/smc600.i
SMC600/smc600.py
smc600-0.0.17.dist-info/licenses/LICENSE
smc600-0.0.17.dist-info/METADATA
smc600-0.0.17.dist-info/WHEEL
smc600-0.0.17.dist-info/top_level.txt
smc600-0.0.17.dist-info/RECORD
